[
  {
    "name": "drakenschedel",
    "soundpath": "sounds/drakenschedel.mp3",
    "points": [5],
    "symbols": ["fossil"],
    "curses": 0,
    "moon": "none",
    "command": "normal",
    "image": "images/cards/light_drakenschedel.png"
  },
  {
    "name": "veer van de zonnesteen feniks",
    "soundpath": "sounds/veer_van_de_zonnesteen_feniks.mp3",
    "points": [3],
    "symbols": ["fossil"],
    "curses": 0,
    "moon": "none",
    "command": "normal",
    "image": "images/cards/light_veer_van_de_zonnesteen_feniks.png"
  },
  {
    "name": "klauw van een mensaap",
    "soundpath": "sounds/klauw_van_een_mensaap.mp3",
    "points": [4],
    "symbols": ["fossil"],
    "curses": 0,
    "moon": "none",
    "command": "normal",
    "image": "images/cards/light_klauw_van_een_mensaap.png"
  },
  {
    "name": "machtige drank der genezing",
    "soundpath": "sounds/machtige_drank_der_genezing.mp3",
    "points": [5],
    "symbols": ["potion"],
    "curses": 0,
    "moon": "none",
    "command": "normal",
    "image": "images/cards/light_machtige_drank_der_genezing.png"
  },
  {
    "name": "krachtdrank",
    "soundpath": "sounds/krachtdrank.mp3",
    "points": [4],
    "symbols": ["potion"],
    "curses": 0,
    "moon": "none",
    "command": "normal",
    "image": "images/cards/light_krachtdrank.png"
  },
  {
    "name": "steen der koningen",
    "soundpath": "sounds/steen_der_koningen.mp3",
    "points": [5],
    "symbols": ["jewel"],
    "curses": 0,
    "moon": "none",
    "command": "normal",
    "image": "images/cards/light_steen_der_koningen.png"
  },
  {
    "name": "liefdesdrank nummer 8",
    "soundpath": "sounds/liefdesdrank_nummer_8.mp3",
    "points": [3],
    "symbols": ["potion"],
    "curses": 0,
    "moon": "none",
    "command": "normal",
    "image": "images/cards/light_liefdesdrank_8.png"
  },
  {
    "name": "het eeuwige hart",
    "soundpath": "sounds/het_eeuwige_hart.mp3",
    "points": [4],
    "symbols": ["jewel"],
    "curses": 0,
    "moon": "none",
    "command": "normal",
    "image": "images/cards/light_het_eeuwige_hart.png"
  },
  {
    "name": "het oog van vala",
    "soundpath": "sounds/het_oog_van_vala.mp3",
    "points": [3],
    "symbols": ["jewel"],
    "curses": 0,
    "moon": "none",
    "command": "normal",
    "image": "images/cards/light_het_oog_van_vala.png"
  },
  {
    "name": "zilveren afgod van hun-batz",
    "soundpath": "sounds/zilveren_afgod_van_hun_batz.mp3",
    "points": [5],
    "symbols": ["artifact"],
    "curses": 0,
    "moon": "none",
    "command": "normal",
    "image": "images/cards/light_zilveren_afgod_van_hun-batz.png"
  },
  {
    "name": "kompas der engelen",
    "soundpath": "sounds/kompas_der_engelen.mp3",
    "points": [4],
    "symbols": ["artifact"],
    "curses": 0,
    "moon": "none",
    "command": "normal",
    "image": "images/cards/light_kompas_der_engelen.png"
  },
  {
    "name": "spreukenboek",
    "soundpath": "sounds/spreukenboek.mp3",
    "points": [5],
    "symbols": ["tome"],
    "curses": 0,
    "moon": "none",
    "command": "normal",
    "image": "images/cards/light_spreukenboek.png"
  },
  {
    "name": "de formules van flemel",
    "soundpath": "sounds/de_formules_van_flemel.mp3",
    "points": [4],
    "symbols": ["tome"],
    "curses": 0,
    "moon": "none",
    "command": "normal",
    "image": "images/cards/light_de_formules_van_flemel.png"
  },
  {
    "name": "het bestiarium van orion",
    "soundpath": "sounds/het_bestiarium_van_orion.mp3",
    "points": [3],
    "symbols": ["tome"],
    "curses": 0,
    "moon": "none",
    "command": "normal",
    "image": "images/cards/light_het_bestiarium_van_orion.png"
  },
  {
    "name": "twijgje van de dageraad boom",
    "soundpath": "sounds/twijgje_van_de_dageraad_boom.mp3",
    "points": [3],
    "symbols": ["artifact"],
    "curses": 0,
    "moon": "none",
    "command": "normal",
    "image": "images/cards/light_twijgje_van_de_dageraad_boom.png"
  },
  {
    "name": "hemelse tarotkaarten",
    "soundpath": "sounds/hemelse_tarotkaarten.mp3",
    "points": [2],
    "symbols": ["wild"],
    "curses": 1,
    "moon": "none",
    "command": "normal",
    "image": "images/cards/light_hemelse_tarotkaarten.png"
  },
  {
    "name": "helse tarotkaarten",
    "soundpath": "sounds/helse_tarotkaarten.mp3",
    "points": [2],
    "symbols": ["wild"],
    "curses": 1,
    "moon": "none",
    "command": "normal",
    "image": "images/cards/light_helse_tarotkaarten.png"
  }
]
